mimesis_factory.py
mimesis_factory-1.2.0.dist-info/LICENSE
mimesis_factory-1.2.0.dist-info/WHEEL
mimesis_factory-1.2.0.dist-info/METADATA
mimesis_factory-1.2.0.dist-info/RECORD
