Metadata-Version: 2.1
Name: mimesis-factory
Version: 1.2.0
Summary: Mimesis integration with factory_boy
Home-page: https://github.com/mimesis-lab/mimesis-factory
License: MIT
Keywords: mimesis,factory_boy,testing,fixtures,fake data,fabric,factory
Author: Nikita Sobolev
Author-email: mail@sobolevn.me
Requires-Python: >=3.6,<4.0
Classifier: License :: OSI Approved :: MIT License
Classifier: Programming Language :: Python :: 3
Classifier: Programming Language :: Python :: 3.6
Classifier: Programming Language :: Python :: 3.7
Classifier: Programming Language :: Python :: 3.8
Requires-Dist: factory-boy (>=2.11,<4.0)
Requires-Dist: mimesis (>=4.0,<5.0)
Project-URL: Repository, https://github.com/mimesis-lab/mimesis-factory
